apteco/__init__.py
apteco/common.py
apteco/cube.py
apteco/datagrid.py
apteco/exceptions.py
apteco/query.py
apteco/session.py
apteco/statistics.py
apteco/tables.py
apteco/variables.py
apteco-0.8.2.dist-info/licenses/LICENSE
apteco-0.8.2.dist-info/METADATA
apteco-0.8.2.dist-info/WHEEL
apteco-0.8.2.dist-info/RECORD
