Metadata-Version: 2.4
Name: apteco
Version: 0.8.2
Summary: A Python package for interacting with Apteco Marketing Suite resources via the Apteco API.
License: Apache-2.0
License-File: LICENSE
Keywords: Apteco,FastStats,Orbit,API,Marketing
Author: Apteco Ltd
Author-email: support@apteco.com
Requires-Python: >=3.10,<3.13
Classifier: Development Status :: 3 - Alpha
Classifier: License :: OSI Approved :: Apache Software License
Classifier: Programming Language :: Python :: 3
Classifier: Programming Language :: Python :: 3.10
Classifier: Programming Language :: Python :: 3.11
Classifier: Programming Language :: Python :: 3.12
Classifier: Programming Language :: Python :: 3 :: Only
Classifier: Programming Language :: Python :: 3.6
Classifier: Programming Language :: Python :: 3.7
Classifier: Programming Language :: Python :: 3.8
Requires-Dist: apteco-api (>=0.3.1,<0.4.0)
Requires-Dist: numpy (>=1.26,<2.0)
Requires-Dist: pandas (>=1.5,<2.0)
Project-URL: Homepage, https://help.apteco.com/python/index.html
Project-URL: Repository, https://github.com/Apteco/py-apteco
